aptos_verify/__init__.py
aptos_verify/cli.py
aptos_verify/config.py
aptos_verify/const.py
aptos_verify/decorators.py
aptos_verify/exceptions.py
aptos_verify/main.py
aptos_verify/memory.py
aptos_verify/move/__init__.py
aptos_verify/move/template/Move.toml
aptos_verify/move/template/Prover.toml
aptos_verify/move/template/lock.lock
aptos_verify/move/template/sources/code.move
aptos_verify/rules/__init__.py
aptos_verify/rules/analysis_code.py
aptos_verify/rules/compare_bytecode.py
aptos_verify/rules/compare_github.py
aptos_verify/rules/compare_local.py
aptos_verify/schemas.py
aptos_verify/utils.py
aptos_verify-1.0.4.dist-info/LICENSE
aptos_verify-1.0.4.dist-info/METADATA
aptos_verify-1.0.4.dist-info/WHEEL
aptos_verify-1.0.4.dist-info/entry_points.txt
aptos_verify-1.0.4.dist-info/RECORD
